llm_tavily.py
llm_tavily-0.0.2.dist-info/licenses/LICENSE
llm_tavily-0.0.2.dist-info/METADATA
llm_tavily-0.0.2.dist-info/WHEEL
llm_tavily-0.0.2.dist-info/entry_points.txt
llm_tavily-0.0.2.dist-info/top_level.txt
llm_tavily-0.0.2.dist-info/RECORD
